{"version": "1", "message": "ERROR: Hidden Testcases server unreachable.", "problem_id": "ads1_week3_exam", "user_id": "Gayatri-Prathyusha", "score": {"sample": {"0": {"execution_time": 0.3460988998413086, "passed": true}, "1": {"execution_time": 0.309542179107666, "passed": true}, "2": {"execution_time": 0.29723381996154785, "passed": false}, "3": {"execution_time": 0.29242491722106934, "passed": false}, "4": {"execution_time": 0.29784107208251953, "passed": false}}}, "check_style_score": "0/1"}